[[["break", [[], [], [], []]], ["skill", [[[46, "plate", 5]], [[78, "tooth", 5]], [[79, "walnut", 5]], [[9, "cluster", 5]], [[48, "powder", 5]], [[32, "gear", 5]], [[17, "feather", 5]], [[7, "claw1", 5]], [[10, "cubes", 1]]]]], [[], [[48, {"item_name": "powder", "needed_num": 15}], [32, {"item_name": "gear", "needed_num": 15}], [46, {"item_name": "plate", "needed_num": 15}], [17, {"item_name": "feather", "needed_num": 15}], [9, {"item_name": "cluster", "needed_num": 15}], [10, {"item_name": "cubes", "needed_num": 3}], [7, {"item_name": "claw1", "needed_num": 15}], [78, {"item_name": "tooth", "needed_num": 15}], [79, {"item_name": "walnut", "needed_num": 15}]]], [[46, "plate", 15], [48, "powder", 15], [78, "tooth", 15], [9, "cluster", 15], [17, "feather", 15], [32, "gear", 15], [79, "walnut", 15], [7, "claw1", 15], [10, "cubes", 3]]]