[[["break", [[[31, "figure7s", 5]], [[31, "figure7s", 12], [78, "tooth", 18]], [[30, "figure7g", 5], [17, "feather", 8], [7, "claw1", 2]], [[30, "figure7g", 12], [46, "plate", 36], [7, "claw1", 4]]]], ["skill", [[[68, "sphere07", 5]], [[68, "sphere07", 12]], [[57, "ruby07", 5]], [[57, "ruby07", 12], [17, "feather", 4]], [[75, "star07", 5], [17, "feather", 8]], [[75, "star07", 12], [78, "tooth", 12]], [[78, "tooth", 24], [48, "powder", 12]], [[48, "powder", 36], [9, "cluster", 24]], [[10, "cubes", 1]]]]], [[[17, {"item_name": "feather", "needed_num": 8}], [78, {"item_name": "tooth", "needed_num": 18}], [7, {"item_name": "claw1", "needed_num": 6}], [46, {"item_name": "plate", "needed_num": 36}], [30, {"item_name": "figure7g", "needed_num": 17}], [31, {"item_name": "figure7s", "needed_num": 17}]], [[48, {"item_name": "powder", "needed_num": 144}], [17, {"item_name": "feather", "needed_num": 36}], [68, {"item_name": "sphere07", "needed_num": 51}], [9, {"item_name": "cluster", "needed_num": 72}], [57, {"item_name": "ruby07", "needed_num": 51}], [10, {"item_name": "cubes", "needed_num": 3}], [75, {"item_name": "star07", "needed_num": 51}], [78, {"item_name": "tooth", "needed_num": 108}]]], [[46, "plate", 36], [48, "powder", 144], [78, "tooth", 126], [9, "cluster", 72], [17, "feather", 44], [7, "claw1", 6], [10, "cubes", 3], [68, "sphere07", 51], [57, "ruby07", 51], [75, "star07", 51], [31, "figure7s", 17], [30, "figure7g", 17]]]