[[["break", [[[23, "figure3s", 4]], [[23, "figure3s", 10], [58, "shell", 6]], [[22, "figure3g", 4], [79, "walnut", 10], [17, "feather", 4]], [[22, "figure3g", 10], [17, "feather", 7], [2, "bakazhen", 24]]]], ["skill", [[[64, "sphere03", 4]], [[64, "sphere03", 10]], [[53, "ruby03", 4]], [[53, "ruby03", 10], [79, "walnut", 5]], [[71, "star03", 4], [79, "walnut", 10]], [[71, "star03", 10], [58, "shell", 4]], [[58, "shell", 8], [81, "yinmao", 3]], [[81, "yinmao", 9], [61, "snake", 16]], [[10, "cubes", 1]]]]], [[[17, {"item_name": "feather", "needed_num": 11}], [2, {"item_name": "bakazhen", "needed_num": 24}], [22, {"item_name": "figure3g", "needed_num": 14}], [23, {"item_name": "figure3s", "needed_num": 14}], [58, {"item_name": "shell", "needed_num": 6}], [79, {"item_name": "walnut", "needed_num": 10}]], [[64, {"item_name": "sphere03", "needed_num": 42}], [81, {"item_name": "yinmao", "needed_num": 36}], [10, {"item_name": "cubes", "needed_num": 3}], [53, {"item_name": "ruby03", "needed_num": 42}], [71, {"item_name": "star03", "needed_num": 42}], [58, {"item_name": "shell", "needed_num": 36}], [61, {"item_name": "snake", "needed_num": 48}], [79, {"item_name": "walnut", "needed_num": 45}]]], [[2, "bakazhen", 24], [17, "feather", 11], [58, "shell", 42], [61, "snake", 48], [79, "walnut", 55], [81, "yinmao", 36], [10, "cubes", 3], [64, "sphere03", 42], [53, "ruby03", 42], [71, "star03", 42], [23, "figure3s", 14], [22, "figure3g", 14]]]