[[["break", [[[25, "figure4s", 4]], [[25, "figure4s", 10], [45, "paper", 6]], [[24, "figure4g", 4], [81, "yinmao", 5], [17, "feather", 4]], [[24, "figure4g", 10], [17, "feather", 7], [33, "gem", 4]]]], ["skill", [[[65, "sphere04", 4]], [[65, "sphere04", 10]], [[54, "ruby04", 4]], [[54, "ruby04", 10], [81, "yinmao", 3]], [[72, "star04", 4], [81, "yinmao", 5]], [[72, "star04", 10], [45, "paper", 4]], [[45, "paper", 8], [82, "zhui", 15]], [[82, "zhui", 45], [36, "heart", 8]], [[10, "cubes", 1]]]]], [[[17, {"item_name": "feather", "needed_num": 11}], [33, {"item_name": "gem", "needed_num": 4}], [81, {"item_name": "yinmao", "needed_num": 5}], [24, {"item_name": "figure4g", "needed_num": 14}], [25, {"item_name": "figure4s", "needed_num": 14}], [45, {"item_name": "paper", "needed_num": 6}]], [[65, {"item_name": "sphere04", "needed_num": 42}], [82, {"item_name": "zhui", "needed_num": 180}], [36, {"item_name": "heart", "needed_num": 24}], [54, {"item_name": "ruby04", "needed_num": 42}], [81, {"item_name": "yinmao", "needed_num": 24}], [72, {"item_name": "star04", "needed_num": 42}], [10, {"item_name": "cubes", "needed_num": 3}], [45, {"item_name": "paper", "needed_num": 36}]]], [[82, "zhui", 180], [17, "feather", 11], [45, "paper", 42], [33, "gem", 4], [36, "heart", 24], [81, "yinmao", 29], [10, "cubes", 3], [65, "sphere04", 42], [54, "ruby04", 42], [72, "star04", 42], [25, "figure4s", 14], [24, "figure4g", 14]]]